{
  "_note": "Group assignments are illustrative. Verify with official FIFA sources at fifa.com. 48 teams, 12 groups of 4.",
  "groups": [
    {
      "id": "A",
      "name": "Group A",
      "teams": [
        { "code": "MEX", "name": "Mexico",      "flag": "рџ‡Ірџ‡Ѕ", "played": 0, "won": 0, "drawn": 0, "lost": 0, "gf": 0, "ga": 0, "gd": 0, "points": 0, "status": "none" },
        { "code": "RSA", "name": "South Africa","flag": "рџ‡їрџ‡¦", "played": 0, "won": 0, "drawn": 0, "lost": 0, "gf": 0, "ga": 0, "gd": 0, "points": 0, "status": "none" },
        { "code": "POL", "name": "Poland",      "flag": "рџ‡µрџ‡±", "played": 0, "won": 0, "drawn": 0, "lost": 0, "gf": 0, "ga": 0, "gd": 0, "points": 0, "status": "none" },
        { "code": "JAM", "name": "Jamaica",     "flag": "рџ‡Їрџ‡І", "played": 0, "won": 0, "drawn": 0, "lost": 0, "gf": 0, "ga": 0, "gd": 0, "points": 0, "status": "none" }
      ]
    },
    {
      "id": "B",
      "name": "Group B",
      "teams": [
        { "code": "USA", "name": "USA",       "flag": "рџ‡єрџ‡ё", "played": 0, "won": 0, "drawn": 0, "lost": 0, "gf": 0, "ga": 0, "gd": 0, "points": 0, "status": "none" },
        { "code": "URU", "name": "Uruguay",   "flag": "рџ‡єрџ‡ѕ", "played": 0, "won": 0, "drawn": 0, "lost": 0, "gf": 0, "ga": 0, "gd": 0, "points": 0, "status": "none" },
        { "code": "EGY", "name": "Egypt",     "flag": "рџ‡Єрџ‡¬", "played": 0, "won": 0, "drawn": 0, "lost": 0, "gf": 0, "ga": 0, "gd": 0, "points": 0, "status": "none" },
        { "code": "AUS", "name": "Australia", "flag": "рџ‡¦рџ‡є", "played": 0, "won": 0, "drawn": 0, "lost": 0, "gf": 0, "ga": 0, "gd": 0, "points": 0, "status": "none" }
      ]
    },
    {
      "id": "C",
      "name": "Group C",
      "teams": [
        { "code": "CAN", "name": "Canada",    "flag": "рџ‡Ёрџ‡¦", "played": 0, "won": 0, "drawn": 0, "lost": 0, "gf": 0, "ga": 0, "gd": 0, "points": 0, "status": "none" },
        { "code": "COL", "name": "Colombia",  "flag": "рџ‡Ёрџ‡ґ", "played": 0, "won": 0, "drawn": 0, "lost": 0, "gf": 0, "ga": 0, "gd": 0, "points": 0, "status": "none" },
        { "code": "MAR", "name": "Morocco",   "flag": "рџ‡Ірџ‡¦", "played": 0, "won": 0, "drawn": 0, "lost": 0, "gf": 0, "ga": 0, "gd": 0, "points": 0, "status": "none" },
        { "code": "KOR", "name": "South Korea","flag": "рџ‡°рџ‡·", "played": 0, "won": 0, "drawn": 0, "lost": 0, "gf": 0, "ga": 0, "gd": 0, "points": 0, "status": "none" }
      ]
    },
    {
      "id": "D",
      "name": "Group D",
      "teams": [
        { "code": "BRA", "name": "Brazil",    "flag": "рџ‡§рџ‡·", "played": 0, "won": 0, "drawn": 0, "lost": 0, "gf": 0, "ga": 0, "gd": 0, "points": 0, "status": "none" },
        { "code": "CHI", "name": "Chile",     "flag": "рџ‡Ёрџ‡±", "played": 0, "won": 0, "drawn": 0, "lost": 0, "gf": 0, "ga": 0, "gd": 0, "points": 0, "status": "none" },
        { "code": "HUN", "name": "Hungary",   "flag": "рџ‡­рџ‡є", "played": 0, "won": 0, "drawn": 0, "lost": 0, "gf": 0, "ga": 0, "gd": 0, "points": 0, "status": "none" },
        { "code": "TUN", "name": "Tunisia",   "flag": "рџ‡№рџ‡і", "played": 0, "won": 0, "drawn": 0, "lost": 0, "gf": 0, "ga": 0, "gd": 0, "points": 0, "status": "none" }
      ]
    },
    {
      "id": "E",
      "name": "Group E",
      "teams": [
        { "code": "ARG", "name": "Argentina", "flag": "рџ‡¦рџ‡·", "played": 0, "won": 0, "drawn": 0, "lost": 0, "gf": 0, "ga": 0, "gd": 0, "points": 0, "status": "none" },
        { "code": "PAR", "name": "Paraguay",  "flag": "рџ‡µрџ‡ѕ", "played": 0, "won": 0, "drawn": 0, "lost": 0, "gf": 0, "ga": 0, "gd": 0, "points": 0, "status": "none" },
        { "code": "TUR", "name": "Turkey",    "flag": "рџ‡№рџ‡·", "played": 0, "won": 0, "drawn": 0, "lost": 0, "gf": 0, "ga": 0, "gd": 0, "points": 0, "status": "none" },
        { "code": "IDN", "name": "Indonesia", "flag": "рџ‡®рџ‡©", "played": 0, "won": 0, "drawn": 0, "lost": 0, "gf": 0, "ga": 0, "gd": 0, "points": 0, "status": "none" }
      ]
    },
    {
      "id": "F",
      "name": "Group F",
      "teams": [
        { "code": "FRA", "name": "France",    "flag": "рџ‡«рџ‡·", "played": 0, "won": 0, "drawn": 0, "lost": 0, "gf": 0, "ga": 0, "gd": 0, "points": 0, "status": "none" },
        { "code": "SRB", "name": "Serbia",    "flag": "рџ‡·рџ‡ё", "played": 0, "won": 0, "drawn": 0, "lost": 0, "gf": 0, "ga": 0, "gd": 0, "points": 0, "status": "none" },
        { "code": "IRN", "name": "Iran",      "flag": "рџ‡®рџ‡·", "played": 0, "won": 0, "drawn": 0, "lost": 0, "gf": 0, "ga": 0, "gd": 0, "points": 0, "status": "none" },
        { "code": "JAM", "name": "Jamaica",   "flag": "рџ‡Їрџ‡І", "played": 0, "won": 0, "drawn": 0, "lost": 0, "gf": 0, "ga": 0, "gd": 0, "points": 0, "status": "none" }
      ]
    },
    {
      "id": "G",
      "name": "Group G",
      "teams": [
        { "code": "ESP", "name": "Spain",     "flag": "рџ‡Єрџ‡ё", "played": 0, "won": 0, "drawn": 0, "lost": 0, "gf": 0, "ga": 0, "gd": 0, "points": 0, "status": "none" },
        { "code": "PER", "name": "Peru",      "flag": "рџ‡µрџ‡Є", "played": 0, "won": 0, "drawn": 0, "lost": 0, "gf": 0, "ga": 0, "gd": 0, "points": 0, "status": "none" },
        { "code": "SCO", "name": "Scotland",  "flag": "рџЏґу Ѓ§у Ѓўу Ѓіу ЃЈу Ѓґу Ѓї", "played": 0, "won": 0, "drawn": 0, "lost": 0, "gf": 0, "ga": 0, "gd": 0, "points": 0, "status": "none" },
        { "code": "SEN", "name": "Senegal",   "flag": "рџ‡ёрџ‡і", "played": 0, "won": 0, "drawn": 0, "lost": 0, "gf": 0, "ga": 0, "gd": 0, "points": 0, "status": "none" }
      ]
    },
    {
      "id": "H",
      "name": "Group H",
      "teams": [
        { "code": "ENG", "name": "England",   "flag": "рџЏґу Ѓ§у Ѓўу ЃҐу Ѓ®у Ѓ§у Ѓї", "played": 0, "won": 0, "drawn": 0, "lost": 0, "gf": 0, "ga": 0, "gd": 0, "points": 0, "status": "none" },
        { "code": "VEN", "name": "Venezuela", "flag": "рџ‡»рџ‡Є", "played": 0, "won": 0, "drawn": 0, "lost": 0, "gf": 0, "ga": 0, "gd": 0, "points": 0, "status": "none" },
        { "code": "POL", "name": "Poland",    "flag": "рџ‡µрџ‡±", "played": 0, "won": 0, "drawn": 0, "lost": 0, "gf": 0, "ga": 0, "gd": 0, "points": 0, "status": "none" },
        { "code": "GHA", "name": "Ghana",     "flag": "рџ‡¬рџ‡­", "played": 0, "won": 0, "drawn": 0, "lost": 0, "gf": 0, "ga": 0, "gd": 0, "points": 0, "status": "none" }
      ]
    },
    {
      "id": "I",
      "name": "Group I",
      "teams": [
        { "code": "POR", "name": "Portugal",  "flag": "рџ‡µрџ‡№", "played": 0, "won": 0, "drawn": 0, "lost": 0, "gf": 0, "ga": 0, "gd": 0, "points": 0, "status": "none" },
        { "code": "BOL", "name": "Bolivia",   "flag": "рџ‡§рџ‡ґ", "played": 0, "won": 0, "drawn": 0, "lost": 0, "gf": 0, "ga": 0, "gd": 0, "points": 0, "status": "none" },
        { "code": "ROU", "name": "Romania",   "flag": "рџ‡·рџ‡ґ", "played": 0, "won": 0, "drawn": 0, "lost": 0, "gf": 0, "ga": 0, "gd": 0, "points": 0, "status": "none" },
        { "code": "NGA", "name": "Nigeria",   "flag": "рџ‡ірџ‡¬", "played": 0, "won": 0, "drawn": 0, "lost": 0, "gf": 0, "ga": 0, "gd": 0, "points": 0, "status": "none" }
      ]
    },
    {
      "id": "J",
      "name": "Group J",
      "teams": [
        { "code": "GER", "name": "Germany",   "flag": "рџ‡©рџ‡Є", "played": 0, "won": 0, "drawn": 0, "lost": 0, "gf": 0, "ga": 0, "gd": 0, "points": 0, "status": "none" },
        { "code": "HON", "name": "Honduras",  "flag": "рџ‡­рџ‡і", "played": 0, "won": 0, "drawn": 0, "lost": 0, "gf": 0, "ga": 0, "gd": 0, "points": 0, "status": "none" },
        { "code": "AUT", "name": "Austria",   "flag": "рџ‡¦рџ‡№", "played": 0, "won": 0, "drawn": 0, "lost": 0, "gf": 0, "ga": 0, "gd": 0, "points": 0, "status": "none" },
        { "code": "CMR", "name": "Cameroon",  "flag": "рџ‡Ёрџ‡І", "played": 0, "won": 0, "drawn": 0, "lost": 0, "gf": 0, "ga": 0, "gd": 0, "points": 0, "status": "none" }
      ]
    },
    {
      "id": "K",
      "name": "Group K",
      "teams": [
        { "code": "NED", "name": "Netherlands","flag": "рџ‡ірџ‡±", "played": 0, "won": 0, "drawn": 0, "lost": 0, "gf": 0, "ga": 0, "gd": 0, "points": 0, "status": "none" },
        { "code": "PAN", "name": "Panama",    "flag": "рџ‡µрџ‡¦", "played": 0, "won": 0, "drawn": 0, "lost": 0, "gf": 0, "ga": 0, "gd": 0, "points": 0, "status": "none" },
        { "code": "UKR", "name": "Ukraine",   "flag": "рџ‡єрџ‡¦", "played": 0, "won": 0, "drawn": 0, "lost": 0, "gf": 0, "ga": 0, "gd": 0, "points": 0, "status": "none" },
        { "code": "ZAF", "name": "South Africa","flag": "рџ‡їрџ‡¦", "played": 0, "won": 0, "drawn": 0, "lost": 0, "gf": 0, "ga": 0, "gd": 0, "points": 0, "status": "none" }
      ]
    },
    {
      "id": "L",
      "name": "Group L",
      "teams": [
        { "code": "CRO", "name": "Croatia",   "flag": "рџ‡­рџ‡·", "played": 0, "won": 0, "drawn": 0, "lost": 0, "gf": 0, "ga": 0, "gd": 0, "points": 0, "status": "none" },
        { "code": "KSA", "name": "Saudi Arabia","flag": "рџ‡ёрџ‡¦", "played": 0, "won": 0, "drawn": 0, "lost": 0, "gf": 0, "ga": 0, "gd": 0, "points": 0, "status": "none" },
        { "code": "JOR", "name": "Jordan",    "flag": "рџ‡Їрџ‡ґ", "played": 0, "won": 0, "drawn": 0, "lost": 0, "gf": 0, "ga": 0, "gd": 0, "points": 0, "status": "none" },
        { "code": "NZL", "name": "New Zealand","flag": "рџ‡ірџ‡ї", "played": 0, "won": 0, "drawn": 0, "lost": 0, "gf": 0, "ga": 0, "gd": 0, "points": 0, "status": "none" }
      ]
    }
  ]
}
