{
  "_note": "City Jump from Kansas City perspective. Scores reflect travel ease, match quality, and city energy FROM KC.",
  "lastUpdated": "2026-05-14T12:00:00-05:00",
  "cities": [
    {
      "id": "kansascity",
      "name": "Kansas City",
      "country": "USA",
      "flag": "🇺🇸",
      "home": true,
      "venue": "Kansas City Stadium",
      "matches": 6,
      "stages": ["Group Stage", "Round of 32", "Quarterfinal"],
      "scores": { "matchQuality": 5, "ticketAccess": 4, "travelEase": 5, "cityEnergy": 5, "overall": 5 },
      "flightFromCity": "Home",
      "hotelNote": "Book now — Quarterfinal weekend will be impossible to find last-minute.",
      "bestFor": "Your home turf and a World Cup Quarterfinal. This is the crown jewel.",
      "tag": "Home base"
    },
    {
      "id": "dallas",
      "name": "Dallas",
      "country": "USA",
      "flag": "🇺🇸",
      "home": false,
      "venue": "AT&T Stadium",
      "matches": 9,
      "stages": ["Group Stage", "Round of 32", "Quarterfinal", "Final"],
      "scores": { "matchQuality": 5, "ticketAccess": 3, "travelEase": 5, "cityEnergy": 4, "overall": 5 },
      "flightFromCity": "1.5 hr flight or 7 hr drive",
      "hotelNote": "Affordable outside downtown Arlington. Book early for Final weekend.",
      "bestFor": "Closest major host city. Shares Group J with KC (Argentina, Algeria). AT&T Stadium hosts the Final.",
      "tag": "Closest major venue"
    },
    {
      "id": "houston",
      "name": "Houston",
      "country": "USA",
      "flag": "🇺🇸",
      "home": false,
      "venue": "NRG Stadium",
      "matches": 6,
      "stages": ["Group Stage", "Round of 32"],
      "scores": { "matchQuality": 4, "ticketAccess": 4, "travelEase": 4, "cityEnergy": 3, "overall": 4 },
      "flightFromCity": "2 hr flight",
      "hotelNote": "Reasonably priced. NRG area has many options.",
      "bestFor": "Another short flight option from KC. Different groups than KC.",
      "tag": "Quick flight"
    },
    {
      "id": "mexicocity",
      "name": "Mexico City",
      "country": "Mexico",
      "flag": "🇲🇽",
      "home": false,
      "venue": "Estadio Azteca",
      "matches": 6,
      "stages": ["Group Stage", "Round of 32"],
      "scores": { "matchQuality": 5, "ticketAccess": 4, "travelEase": 4, "cityEnergy": 5, "overall": 5 },
      "flightFromCity": "2.5 hr direct flight",
      "hotelNote": "Affordable compared to US cities. Currency is favorable for US travelers.",
      "bestFor": "Azteca hosts the opening match (Mexico vs South Africa, June 11). Bucket-list venue from KC in under 3 hrs.",
      "tag": "Bucket-list venue"
    },
    {
      "id": "losangeles",
      "name": "Los Angeles",
      "country": "USA",
      "flag": "🇺🇸",
      "home": false,
      "venue": "SoFi Stadium",
      "matches": 8,
      "stages": ["Group Stage", "Round of 32", "Quarterfinal"],
      "scores": { "matchQuality": 5, "ticketAccess": 2, "travelEase": 3, "cityEnergy": 5, "overall": 4 },
      "flightFromCity": "2.5 hr flight",
      "hotelNote": "Expensive. Consider Airbnb in Inglewood or nearby Hollywood Park.",
      "bestFor": "USA opens its World Cup here vs Paraguay. Top-tier match quality.",
      "tag": "USA's opener"
    },
    {
      "id": "seattle",
      "name": "Seattle",
      "country": "USA",
      "flag": "🇺🇸",
      "home": false,
      "venue": "Lumen Field",
      "matches": 6,
      "stages": ["Group Stage", "Round of 32", "Round of 16"],
      "scores": { "matchQuality": 4, "ticketAccess": 3, "travelEase": 3, "cityEnergy": 4, "overall": 4 },
      "flightFromCity": "3 hr flight",
      "hotelNote": "Book early — Seattle hotels are expensive during match weeks.",
      "bestFor": "USA vs Australia and Egypt vs Iran night match. R16 at Lumen Field. Pacific Northwest energy.",
      "tag": "USA match city"
    },
    {
      "id": "vancouver",
      "name": "Vancouver",
      "country": "Canada",
      "flag": "🇨🇦",
      "home": false,
      "venue": "BC Place",
      "matches": 6,
      "stages": ["Group Stage", "Round of 32"],
      "scores": { "matchQuality": 4, "ticketAccess": 4, "travelEase": 3, "cityEnergy": 4, "overall": 4 },
      "flightFromCity": "3 hr flight (via Seattle or direct)",
      "hotelNote": "Reasonably priced vs US cities. Canadian dollar is favorable.",
      "bestFor": "Canada HQ. Group B (Canada, Switzerland, Qatar, Bosnia). International experience without leaving North America.",
      "tag": "Canada HQ"
    },
    {
      "id": "atlanta",
      "name": "Atlanta",
      "country": "USA",
      "flag": "🇺🇸",
      "home": false,
      "venue": "Mercedes-Benz Stadium",
      "matches": 6,
      "stages": ["Group Stage", "Round of 32"],
      "scores": { "matchQuality": 4, "ticketAccess": 4, "travelEase": 3, "cityEnergy": 4, "overall": 3 },
      "flightFromCity": "2.5 hr flight",
      "hotelNote": "Good hotel options downtown near the stadium.",
      "bestFor": "Southeast hub. Different groups than KC. World-class soccer venue.",
      "tag": "Southeast hub"
    }
  ]
}
